{
  "source": "AI预测 + 真实数据",
  "generatedAt": "2026-05-25T12:22:53.635Z",
  "date": "2026-05-25",
  "count": 11,
  "items": [
    {
      "videoId": "3xpgtbzcea8x4zk",
      "title": "“台独”是破坏台海和平的罪魁祸首",
      "sourceUrl": "https://www.kuaishou.com/short-video/3xpgtbzcea8x4zk",
      "authorName": "国防部发布",
      "likeCount": 21873,
      "commentCount": 0,
      "explosionRate": 85,
      "trend": "rising",
      "hookType": "冲突",
      "category": [
        "时政",
        "军事",
        "社会热点"
      ],
      "estimatedTime": "正在爆发"
    },
    {
      "videoId": "3x6yy3d6gpuvgym",
      "title": "父亲去世12年，银行突然来催债2万3千多，本金才7千，女儿发出三连问：12年为何从不通知？如何证明是父亲生前消费？有没有义务还债？@快手热点(O3xddgkd5fav5if9) #父亲去世12年银行突然来催债 ",
      "sourceUrl": "https://www.kuaishou.com/short-video/3x6yy3d6gpuvgym",
      "authorName": "小强说",
      "likeCount": 5010,
      "commentCount": 0,
      "explosionRate": 75,
      "trend": "rising",
      "hookType": "冲突",
      "category": [
        "社会热点",
        "法律科普",
        "家庭伦理"
      ],
      "estimatedTime": "1-2小时"
    },
    {
      "videoId": "3x7p2x6buzsup8i",
      "title": "写个数字7，只要剪一刀，就能轻松剪出双喜字，小朋友也可以轻松学会，快试试吧#亲子手工#剪纸教程 #双喜剪纸 #幼儿园手工",
      "sourceUrl": "https://www.kuaishou.com/short-video/3x7p2x6buzsup8i",
      "authorName": "小贤手工",
      "likeCount": 2919,
      "commentCount": 0,
      "explosionRate": 75,
      "trend": "rising",
      "hookType": "爽点",
      "category": [
        "亲子教育",
        "生活技巧",
        "手工教程"
      ],
      "estimatedTime": "1-2小时"
    },
    {
      "videoId": "3xbkrubrwc956bc",
      "title": "湖南人小时候的超能力 #湖南 #超能力",
      "sourceUrl": "https://www.kuaishou.com/short-video/3xbkrubrwc956bc",
      "authorName": "邬天宇",
      "likeCount": 29549,
      "commentCount": 0,
      "explosionRate": 65,
      "trend": "stable",
      "hookType": "共情",
      "category": [
        "生活/怀旧",
        "地域文化",
        "搞笑/趣味"
      ],
      "estimatedTime": "2-4小时"
    },
    {
      "videoId": "3xq86qh7jm8c8ne",
      "title": "没事不要和任何人搅合在一起 #人生忠告 #情感共鸣 #知识播种计划 ",
      "sourceUrl": "https://www.kuaishou.com/short-video/3xq86qh7jm8c8ne",
      "authorName": "董超育儿现场",
      "likeCount": 2811,
      "commentCount": 0,
      "explosionRate": 65,
      "trend": "stable",
      "hookType": "共情",
      "category": [
        "情感",
        "人生感悟",
        "知识分享"
      ],
      "estimatedTime": "2-4小时"
    },
    {
      "videoId": "3xyqjhvtzweik84",
      "title": "是谁和我说零号大坝会出手机的！！！ #幸福乡村春耕季 #花式过五一 #三角洲 #三角洲行动  @马大哈奇遇记(O3xryu36qu4xjmvw) ",
      "sourceUrl": "https://www.kuaishou.com/short-video/3xyqjhvtzweik84",
      "authorName": "黑大帅历险记",
      "likeCount": 11060,
      "commentCount": 0,
      "explosionRate": 65,
      "trend": "stable",
      "hookType": "冲突",
      "category": [
        "游戏",
        "搞笑",
        "吐槽"
      ],
      "estimatedTime": "2-4小时"
    },
    {
      "videoId": "3x4ei4qffmvegxs",
      "title": "今天可能位置没选对没钓到龙虾，今天买了点做了个麻辣龙虾看着还不错吧，你们老家河里能掉龙虾了没？#农村守护人 #三农 #记录真实生活",
      "sourceUrl": "https://www.kuaishou.com/short-video/3x4ei4qffmvegxs",
      "authorName": "李会儿、、",
      "likeCount": 7407,
      "commentCount": 0,
      "explosionRate": 65,
      "trend": "stable",
      "hookType": "共情",
      "category": [
        "三农",
        "美食",
        "生活记录"
      ],
      "estimatedTime": "2-4小时"
    },
    {
      "videoId": "3x7x3duw8avf8ui",
      "title": "#快成长计划 #潮流生活成长之星 #骗你生女儿",
      "sourceUrl": "https://www.kuaishou.com/short-video/3x7x3duw8avf8ui",
      "authorName": "小金果宝贝",
      "likeCount": 12372,
      "commentCount": 0,
      "explosionRate": 65,
      "trend": "stable",
      "hookType": "共情",
      "category": [
        "亲子萌娃",
        "生活记录"
      ],
      "estimatedTime": "2-4小时"
    },
    {
      "videoId": "3xsdvktawhfnia2",
      "title": "去派出所报警被大声嚷嚷怎么办 #维权  #老铁财富密码 #老铁看热点",
      "sourceUrl": "https://www.kuaishou.com/short-video/3xsdvktawhfnia2",
      "authorName": "周沫讲理财",
      "likeCount": 29652,
      "commentCount": 0,
      "explosionRate": 65,
      "trend": "rising",
      "hookType": "冲突",
      "category": [
        "社会热点",
        "生活技巧",
        "法律维权"
      ],
      "estimatedTime": "2-4小时"
    },
    {
      "videoId": "3xnhf6cxvwbhcvq",
      "title": "#快聊新闻 #五一充电市集 #喜爱度激励计划 #灼见计划 @快手粉条(O3xhcy6vhfzcu3qe) @快手创作者中心(O3xrgtux2ehryffe) @快手热点(O3xddgkd5fav5if9) @快手主持人(O3xnewxpguishmsc)",
      "sourceUrl": "https://www.kuaishou.com/short-video/3xnhf6cxvwbhcvq",
      "authorName": "我是大梅",
      "likeCount": 9825,
      "commentCount": 0,
      "explosionRate": 65,
      "trend": "stable",
      "hookType": "共情",
      "category": [
        "生活记录",
        "平台活动"
      ],
      "estimatedTime": "2-4小时"
    },
    {
      "videoId": "3xfv3snjgtqh6u6",
      "title": " @穗岁剧场(O3xc6eti7hmk2qzm) 的精彩视频",
      "sourceUrl": "https://www.kuaishou.com/short-video/3xfv3snjgtqh6u6",
      "authorName": "穗岁剧场",
      "likeCount": 13440,
      "commentCount": 0,
      "explosionRate": 65,
      "trend": "stable",
      "hookType": "悬念",
      "category": [
        "短剧",
        "剧情"
      ],
      "estimatedTime": "2-4小时"
    }
  ]
}